jtools/__init__.py
jtools/consts.py
jtools/migrations.py
jtools/utils.py
jtools/data/trddt_DF.csv
jtools/data/trddt_SH.csv
jtools/data/trddt_SZ.csv
jtools/data/trddt_ZF.csv
dsf_jtools-0.1.8.dist-info/METADATA
dsf_jtools-0.1.8.dist-info/WHEEL
dsf_jtools-0.1.8.dist-info/top_level.txt
dsf_jtools-0.1.8.dist-info/RECORD
